memvid_rs/__init__.py
memvid_rs/_memvid_rs.abi3.so
memvid_rs-2.0.4.dist-info/METADATA
memvid_rs-2.0.4.dist-info/WHEEL
memvid_rs-2.0.4.dist-info/licenses/LICENSE
memvid_rs-2.0.4.dist-info/RECORD
