Metadata-Version: 2.4
Name: memvid-rs
Version: 2.0.4
Classifier: Programming Language :: Rust
Classifier: Programming Language :: Python :: Implementation :: CPython
Classifier: Programming Language :: Python :: Implementation :: PyPy
Classifier: License :: OSI Approved :: MIT License
Classifier: Topic :: Software Development :: Libraries :: Python Modules
Classifier: Topic :: Scientific/Engineering :: Artificial Intelligence
Classifier: Topic :: Multimedia :: Video
Requires-Dist: numpy>=1.20.0
Requires-Dist: sentence-transformers>=2.2.0 ; extra == 'full'
Requires-Dist: faiss-cpu>=1.7.0 ; extra == 'full'
Requires-Dist: pypdf2>=3.0.0 ; extra == 'full'
Provides-Extra: full
License-File: LICENSE
Summary: High-performance AI memory library with full-text and semantic search (Rust bindings for memvid v2)
Author-email: DrivenByCode <jaykey1004@gmail.com>
License: MIT
Requires-Python: >=3.8
Project-URL: Homepage, https://github.com/drivenbycode/memvid-rs
Project-URL: Repository, https://github.com/drivenbycode/memvid-rs
